<annotation>
	<folder>tomato</folder>
	<filename>tomato-166.jpg</filename>
	<path>D:\Tomato downloaded\All tomato pics\tomato\tomato-166.jpg</path>
	<source>
		<database>Unknown</database>
	</source>
	<size>
		<width>4312</width>
		<height>5760</height>
		<depth>3</depth>
	</size>
	<segmented>0</segmented>
	<object>
		<name>LS</name>
		<pose>Unspecified</pose>
		<truncated>0</truncated>
		<difficult>0</difficult>
		<bndbox>
			<xmin>1987</xmin>
			<ymin>2486</ymin>
			<xmax>2475</xmax>
			<ymax>3211</ymax>
		</bndbox>
	</object>
	<object>
		<name>LB</name>
		<pose>Unspecified</pose>
		<truncated>1</truncated>
		<difficult>0</difficult>
		<bndbox>
			<xmin>3419</xmin>
			<ymin>1961</ymin>
			<xmax>4312</xmax>
			<ymax>4292</ymax>
		</bndbox>
	</object>
	<object>
		<name>LB</name>
		<pose>Unspecified</pose>
		<truncated>0</truncated>
		<difficult>0</difficult>
		<bndbox>
			<xmin>1162</xmin>
			<ymin>3273</ymin>
			<xmax>2312</xmax>
			<ymax>4205</ymax>
		</bndbox>
	</object>
	<object>
		<name>TLM</name>
		<pose>Unspecified</pose>
		<truncated>0</truncated>
		<difficult>0</difficult>
		<bndbox>
			<xmin>881</xmin>
			<ymin>2248</ymin>
			<xmax>1456</xmax>
			<ymax>2717</ymax>
		</bndbox>
	</object>
	<object>
		<name>TLM</name>
		<pose>Unspecified</pose>
		<truncated>0</truncated>
		<difficult>0</difficult>
		<bndbox>
			<xmin>1858</xmin>
			<ymin>1366</ymin>
			<xmax>2275</xmax>
			<ymax>1974</ymax>
		</bndbox>
	</object>
	<object>
		<name>LB</name>
		<pose>Unspecified</pose>
		<truncated>0</truncated>
		<difficult>0</difficult>
		<bndbox>
			<xmin>644</xmin>
			<ymin>7</ymin>
			<xmax>1019</xmax>
			<ymax>288</ymax>
		</bndbox>
	</object>
	<object>
		<name>TLM</name>
		<pose>Unspecified</pose>
		<truncated>0</truncated>
		<difficult>0</difficult>
		<bndbox>
			<xmin>1839</xmin>
			<ymin>493</ymin>
			<xmax>2114</xmax>
			<ymax>796</ymax>
		</bndbox>
	</object>
	<object>
		<name>TLM</name>
		<pose>Unspecified</pose>
		<truncated>0</truncated>
		<difficult>0</difficult>
		<bndbox>
			<xmin>2046</xmin>
			<ymin>2649</ymin>
			<xmax>2320</xmax>
			<ymax>3116</ymax>
		</bndbox>
	</object>
	<object>
		<name>TLM</name>
		<pose>Unspecified</pose>
		<truncated>0</truncated>
		<difficult>0</difficult>
		<bndbox>
			<xmin>1490</xmin>
			<ymin>2323</ymin>
			<xmax>1784</xmax>
			<ymax>2586</ymax>
		</bndbox>
	</object>
</annotation>
