<annotation>
	<folder>tomato</folder>
	<filename>tomato-977.jpg</filename>
	<path>D:\Tomato downloaded\All tomato pics\tomato\tomato-977.jpg</path>
	<source>
		<database>Unknown</database>
	</source>
	<size>
		<width>4312</width>
		<height>5760</height>
		<depth>3</depth>
	</size>
	<segmented>0</segmented>
	<object>
		<name>LB</name>
		<pose>Unspecified</pose>
		<truncated>1</truncated>
		<difficult>0</difficult>
		<bndbox>
			<xmin>2726</xmin>
			<ymin>1</ymin>
			<xmax>3771</xmax>
			<ymax>1345</ymax>
		</bndbox>
	</object>
	<object>
		<name>EB</name>
		<pose>Unspecified</pose>
		<truncated>0</truncated>
		<difficult>0</difficult>
		<bndbox>
			<xmin>1819</xmin>
			<ymin>2718</ymin>
			<xmax>2634</xmax>
			<ymax>3168</ymax>
		</bndbox>
	</object>
	<object>
		<name>TLM</name>
		<pose>Unspecified</pose>
		<truncated>0</truncated>
		<difficult>0</difficult>
		<bndbox>
			<xmin>3276</xmin>
			<ymin>3857</ymin>
			<xmax>3457</xmax>
			<ymax>4076</ymax>
		</bndbox>
	</object>
	<object>
		<name>TLM</name>
		<pose>Unspecified</pose>
		<truncated>0</truncated>
		<difficult>0</difficult>
		<bndbox>
			<xmin>2572</xmin>
			<ymin>3826</ymin>
			<xmax>3459</xmax>
			<ymax>4608</ymax>
		</bndbox>
	</object>
	<object>
		<name>TLM</name>
		<pose>Unspecified</pose>
		<truncated>0</truncated>
		<difficult>0</difficult>
		<bndbox>
			<xmin>1599</xmin>
			<ymin>4518</ymin>
			<xmax>1911</xmax>
			<ymax>4718</ymax>
		</bndbox>
	</object>
	<object>
		<name>TBC</name>
		<pose>Unspecified</pose>
		<truncated>0</truncated>
		<difficult>0</difficult>
		<bndbox>
			<xmin>1438</xmin>
			<ymin>4857</ymin>
			<xmax>1888</xmax>
			<ymax>5118</ymax>
		</bndbox>
	</object>
	<object>
		<name>TLM</name>
		<pose>Unspecified</pose>
		<truncated>0</truncated>
		<difficult>0</difficult>
		<bndbox>
			<xmin>2719</xmin>
			<ymin>4641</ymin>
			<xmax>3294</xmax>
			<ymax>4982</ymax>
		</bndbox>
	</object>
	<object>
		<name>TBC</name>
		<pose>Unspecified</pose>
		<truncated>0</truncated>
		<difficult>0</difficult>
		<bndbox>
			<xmin>2256</xmin>
			<ymin>5118</ymin>
			<xmax>2678</xmax>
			<ymax>5343</ymax>
		</bndbox>
	</object>
	<object>
		<name>TLM</name>
		<pose>Unspecified</pose>
		<truncated>0</truncated>
		<difficult>0</difficult>
		<bndbox>
			<xmin>1345</xmin>
			<ymin>3165</ymin>
			<xmax>2854</xmax>
			<ymax>3440</ymax>
		</bndbox>
	</object>
	<object>
		<name>LS</name>
		<pose>Unspecified</pose>
		<truncated>0</truncated>
		<difficult>0</difficult>
		<bndbox>
			<xmin>2129</xmin>
			<ymin>4453</ymin>
			<xmax>2406</xmax>
			<ymax>5049</ymax>
		</bndbox>
	</object>
	<object>
		<name>LB</name>
		<pose>Unspecified</pose>
		<truncated>1</truncated>
		<difficult>0</difficult>
		<bndbox>
			<xmin>4060</xmin>
			<ymin>2671</ymin>
			<xmax>4312</xmax>
			<ymax>2997</ymax>
		</bndbox>
	</object>
</annotation>
