<annotation>
	<folder>tomato</folder>
	<filename>tomato-17.jpg</filename>
	<path>D:\Tomato downloaded\All tomato pics\tomato\tomato-17.jpg</path>
	<source>
		<database>Unknown</database>
	</source>
	<size>
		<width>4312</width>
		<height>5760</height>
		<depth>3</depth>
	</size>
	<segmented>0</segmented>
	<object>
		<name>LB</name>
		<pose>Unspecified</pose>
		<truncated>0</truncated>
		<difficult>0</difficult>
		<bndbox>
			<xmin>1381</xmin>
			<ymin>4013</ymin>
			<xmax>1789</xmax>
			<ymax>4380</ymax>
		</bndbox>
	</object>
	<object>
		<name>LB</name>
		<pose>Unspecified</pose>
		<truncated>0</truncated>
		<difficult>0</difficult>
		<bndbox>
			<xmin>2042</xmin>
			<ymin>3880</ymin>
			<xmax>2214</xmax>
			<ymax>4182</ymax>
		</bndbox>
	</object>
	<object>
		<name>LB</name>
		<pose>Unspecified</pose>
		<truncated>0</truncated>
		<difficult>0</difficult>
		<bndbox>
			<xmin>1250</xmin>
			<ymin>3249</ymin>
			<xmax>1511</xmax>
			<ymax>3735</ymax>
		</bndbox>
	</object>
	<object>
		<name>LB</name>
		<pose>Unspecified</pose>
		<truncated>0</truncated>
		<difficult>0</difficult>
		<bndbox>
			<xmin>2500</xmin>
			<ymin>4513</ymin>
			<xmax>2906</xmax>
			<ymax>4913</ymax>
		</bndbox>
	</object>
	<object>
		<name>LB</name>
		<pose>Unspecified</pose>
		<truncated>0</truncated>
		<difficult>0</difficult>
		<bndbox>
			<xmin>1556</xmin>
			<ymin>3368</ymin>
			<xmax>1700</xmax>
			<ymax>3482</ymax>
		</bndbox>
	</object>
	<object>
		<name>LB</name>
		<pose>Unspecified</pose>
		<truncated>0</truncated>
		<difficult>0</difficult>
		<bndbox>
			<xmin>2119</xmin>
			<ymin>2585</ymin>
			<xmax>2269</xmax>
			<ymax>2827</ymax>
		</bndbox>
	</object>
	<object>
		<name>ND-LB</name>
		<pose>Unspecified</pose>
		<truncated>0</truncated>
		<difficult>0</difficult>
		<bndbox>
			<xmin>3950</xmin>
			<ymin>4396</ymin>
			<xmax>4303</xmax>
			<ymax>5141</ymax>
		</bndbox>
	</object>
	<object>
		<name>EB</name>
		<pose>Unspecified</pose>
		<truncated>0</truncated>
		<difficult>0</difficult>
		<bndbox>
			<xmin>3762</xmin>
			<ymin>4641</ymin>
			<xmax>3945</xmax>
			<ymax>4784</ymax>
		</bndbox>
	</object>
	<object>
		<name>ND</name>
		<pose>Unspecified</pose>
		<truncated>0</truncated>
		<difficult>0</difficult>
		<bndbox>
			<xmin>3536</xmin>
			<ymin>4868</ymin>
			<xmax>4069</xmax>
			<ymax>5285</ymax>
		</bndbox>
	</object>
	<object>
		<name>LB</name>
		<pose>Unspecified</pose>
		<truncated>1</truncated>
		<difficult>0</difficult>
		<bndbox>
			<xmin>3114</xmin>
			<ymin>4927</ymin>
			<xmax>3714</xmax>
			<ymax>5760</ymax>
		</bndbox>
	</object>
	<object>
		<name>LB</name>
		<pose>Unspecified</pose>
		<truncated>0</truncated>
		<difficult>0</difficult>
		<bndbox>
			<xmin>2536</xmin>
			<ymin>5207</ymin>
			<xmax>3011</xmax>
			<ymax>5755</ymax>
		</bndbox>
	</object>
	<object>
		<name>TLM</name>
		<pose>Unspecified</pose>
		<truncated>0</truncated>
		<difficult>0</difficult>
		<bndbox>
			<xmin>328</xmin>
			<ymin>4307</ymin>
			<xmax>744</xmax>
			<ymax>4599</ymax>
		</bndbox>
	</object>
	<object>
		<name>TLM</name>
		<pose>Unspecified</pose>
		<truncated>0</truncated>
		<difficult>0</difficult>
		<bndbox>
			<xmin>347</xmin>
			<ymin>4643</ymin>
			<xmax>914</xmax>
			<ymax>5005</ymax>
		</bndbox>
	</object>
	<object>
		<name>LB</name>
		<pose>Unspecified</pose>
		<truncated>0</truncated>
		<difficult>0</difficult>
		<bndbox>
			<xmin>2296</xmin>
			<ymin>2213</ymin>
			<xmax>2541</xmax>
			<ymax>2591</ymax>
		</bndbox>
	</object>
</annotation>
