<annotation>
	<folder>tomato</folder>
	<filename>tomato-1025.jpg</filename>
	<path>D:\Tomato downloaded\All tomato pics\tomato\tomato-1025.jpg</path>
	<source>
		<database>Unknown</database>
	</source>
	<size>
		<width>4312</width>
		<height>5760</height>
		<depth>3</depth>
	</size>
	<segmented>0</segmented>
	<object>
		<name>TBC</name>
		<pose>Unspecified</pose>
		<truncated>0</truncated>
		<difficult>0</difficult>
		<bndbox>
			<xmin>1919</xmin>
			<ymin>2411</ymin>
			<xmax>2700</xmax>
			<ymax>4461</ymax>
		</bndbox>
	</object>
	<object>
		<name>LS</name>
		<pose>Unspecified</pose>
		<truncated>0</truncated>
		<difficult>0</difficult>
		<bndbox>
			<xmin>700</xmin>
			<ymin>1430</ymin>
			<xmax>2025</xmax>
			<ymax>2780</ymax>
		</bndbox>
	</object>
	<object>
		<name>TBC</name>
		<pose>Unspecified</pose>
		<truncated>0</truncated>
		<difficult>0</difficult>
		<bndbox>
			<xmin>2881</xmin>
			<ymin>2392</ymin>
			<xmax>3356</xmax>
			<ymax>3442</ymax>
		</bndbox>
	</object>
	<object>
		<name>TLM</name>
		<pose>Unspecified</pose>
		<truncated>0</truncated>
		<difficult>0</difficult>
		<bndbox>
			<xmin>3675</xmin>
			<ymin>286</ymin>
			<xmax>4137</xmax>
			<ymax>805</ymax>
		</bndbox>
	</object>
	<object>
		<name>TBC</name>
		<pose>Unspecified</pose>
		<truncated>0</truncated>
		<difficult>0</difficult>
		<bndbox>
			<xmin>4015</xmin>
			<ymin>2084</ymin>
			<xmax>4299</xmax>
			<ymax>2411</ymax>
		</bndbox>
	</object>
	<object>
		<name>LS</name>
		<pose>Unspecified</pose>
		<truncated>0</truncated>
		<difficult>0</difficult>
		<bndbox>
			<xmin>2014</xmin>
			<ymin>2835</ymin>
			<xmax>2564</xmax>
			<ymax>3032</ymax>
		</bndbox>
	</object>
	<object>
		<name>LS</name>
		<pose>Unspecified</pose>
		<truncated>0</truncated>
		<difficult>0</difficult>
		<bndbox>
			<xmin>2747</xmin>
			<ymin>1857</ymin>
			<xmax>3014</xmax>
			<ymax>2413</ymax>
		</bndbox>
	</object>
</annotation>
