<annotation>
	<folder>tomato frag</folder>
	<filename>tomato-2612.jpg</filename>
	<path>G:\samin\tomato frag\tomato-2612.jpg</path>
	<source>
		<database>Unknown</database>
	</source>
	<size>
		<width>4312</width>
		<height>5760</height>
		<depth>3</depth>
	</size>
	<segmented>0</segmented>
	<object>
		<name>TBC</name>
		<pose>Unspecified</pose>
		<truncated>0</truncated>
		<difficult>0</difficult>
		<bndbox>
			<xmin>1510</xmin>
			<ymin>2489</ymin>
			<xmax>2377</xmax>
			<ymax>3556</ymax>
		</bndbox>
	</object>
	<object>
		<name>TBC</name>
		<pose>Unspecified</pose>
		<truncated>0</truncated>
		<difficult>0</difficult>
		<bndbox>
			<xmin>2639</xmin>
			<ymin>2213</ymin>
			<xmax>2815</xmax>
			<ymax>2480</ymax>
		</bndbox>
	</object>
	<object>
		<name>TBC</name>
		<pose>Unspecified</pose>
		<truncated>0</truncated>
		<difficult>0</difficult>
		<bndbox>
			<xmin>2686</xmin>
			<ymin>1485</ymin>
			<xmax>3410</xmax>
			<ymax>2480</ymax>
		</bndbox>
	</object>
	<object>
		<name>TBC</name>
		<pose>Unspecified</pose>
		<truncated>1</truncated>
		<difficult>0</difficult>
		<bndbox>
			<xmin>2701</xmin>
			<ymin>1</ymin>
			<xmax>3537</xmax>
			<ymax>434</ymax>
		</bndbox>
	</object>
</annotation>
