<annotation>
	<folder>capsicum</folder>
	<filename>capsicum-699.jpg</filename>
	<path>D:\leafimg\capsicum\capsicum-699.jpg</path>
	<source>
		<database>Unknown</database>
	</source>
	<size>
		<width>4312</width>
		<height>5760</height>
		<depth>3</depth>
	</size>
	<segmented>0</segmented>
	<object>
		<name>INS</name>
		<pose>Unspecified</pose>
		<truncated>0</truncated>
		<difficult>0</difficult>
		<bndbox>
			<xmin>3215</xmin>
			<ymin>3736</ymin>
			<xmax>3928</xmax>
			<ymax>4074</ymax>
		</bndbox>
	</object>
	<object>
		<name>INS</name>
		<pose>Unspecified</pose>
		<truncated>0</truncated>
		<difficult>0</difficult>
		<bndbox>
			<xmin>2684</xmin>
			<ymin>4324</ymin>
			<xmax>3778</xmax>
			<ymax>4968</ymax>
		</bndbox>
	</object>
	<object>
		<name>LCV</name>
		<pose>Unspecified</pose>
		<truncated>0</truncated>
		<difficult>0</difficult>
		<bndbox>
			<xmin>47</xmin>
			<ymin>37</ymin>
			<xmax>3909</xmax>
			<ymax>4368</ymax>
		</bndbox>
	</object>
	<object>
		<name>INS</name>
		<pose>Unspecified</pose>
		<truncated>0</truncated>
		<difficult>0</difficult>
		<bndbox>
			<xmin>1284</xmin>
			<ymin>93</ymin>
			<xmax>2003</xmax>
			<ymax>643</ymax>
		</bndbox>
	</object>
	<object>
		<name>LCV</name>
		<pose>Unspecified</pose>
		<truncated>1</truncated>
		<difficult>0</difficult>
		<bndbox>
			<xmin>1815</xmin>
			<ymin>4630</ymin>
			<xmax>2740</xmax>
			<ymax>5760</ymax>
		</bndbox>
	</object>
</annotation>
