<annotation>
	<folder>images</folder>
	<filename>capsicum-10.jpg</filename>
	<path>E:\mixed\capsicum\images\capsicum-10.jpg</path>
	<source>
		<database>Unknown</database>
	</source>
	<size>
		<width>4312</width>
		<height>5760</height>
		<depth>3</depth>
	</size>
	<segmented>0</segmented>
	<object>
		<name>BLS</name>
		<pose>Unspecified</pose>
		<truncated>0</truncated>
		<difficult>0</difficult>
		<bndbox>
			<xmin>591</xmin>
			<ymin>2387</ymin>
			<xmax>2965</xmax>
			<ymax>5425</ymax>
		</bndbox>
	</object>
</annotation>
