<annotation>
	<folder>Capsicum frag</folder>
	<filename>capsicum-1193.jpg</filename>
	<path>G:\samin\Capsicum frag\capsicum-1193.jpg</path>
	<source>
		<database>Unknown</database>
	</source>
	<size>
		<width>4312</width>
		<height>5760</height>
		<depth>3</depth>
	</size>
	<segmented>0</segmented>
	<object>
		<name>ND</name>
		<pose>Unspecified</pose>
		<truncated>0</truncated>
		<difficult>0</difficult>
		<bndbox>
			<xmin>410</xmin>
			<ymin>761</ymin>
			<xmax>3163</xmax>
			<ymax>2832</ymax>
		</bndbox>
	</object>
</annotation>
