<annotation>
	<folder>images</folder>
	<filename>potato-1894.jpg</filename>
	<path>E:\mixed\potato\images\potato-1894.jpg</path>
	<source>
		<database>Unknown</database>
	</source>
	<size>
		<width>5760</width>
		<height>4312</height>
		<depth>3</depth>
	</size>
	<segmented>0</segmented>
	<object>
		<name>LB</name>
		<pose>Unspecified</pose>
		<truncated>0</truncated>
		<difficult>0</difficult>
		<bndbox>
			<xmin>3251</xmin>
			<ymin>1424</ymin>
			<xmax>3689</xmax>
			<ymax>1614</ymax>
		</bndbox>
	</object>
	<object>
		<name>LB</name>
		<pose>Unspecified</pose>
		<truncated>0</truncated>
		<difficult>0</difficult>
		<bndbox>
			<xmin>3062</xmin>
			<ymin>1569</ymin>
			<xmax>3207</xmax>
			<ymax>1719</ymax>
		</bndbox>
	</object>
	<object>
		<name>LB</name>
		<pose>Unspecified</pose>
		<truncated>0</truncated>
		<difficult>0</difficult>
		<bndbox>
			<xmin>2949</xmin>
			<ymin>1809</ymin>
			<xmax>3104</xmax>
			<ymax>2021</ymax>
		</bndbox>
	</object>
	<object>
		<name>LB</name>
		<pose>Unspecified</pose>
		<truncated>0</truncated>
		<difficult>0</difficult>
		<bndbox>
			<xmin>2926</xmin>
			<ymin>2260</ymin>
			<xmax>3291</xmax>
			<ymax>2500</ymax>
		</bndbox>
	</object>
	<object>
		<name>LB</name>
		<pose>Unspecified</pose>
		<truncated>0</truncated>
		<difficult>0</difficult>
		<bndbox>
			<xmin>2786</xmin>
			<ymin>2454</ymin>
			<xmax>3014</xmax>
			<ymax>2720</ymax>
		</bndbox>
	</object>
	<object>
		<name>LB</name>
		<pose>Unspecified</pose>
		<truncated>0</truncated>
		<difficult>0</difficult>
		<bndbox>
			<xmin>2449</xmin>
			<ymin>1746</ymin>
			<xmax>2840</xmax>
			<ymax>2200</ymax>
		</bndbox>
	</object>
	<object>
		<name>LB</name>
		<pose>Unspecified</pose>
		<truncated>0</truncated>
		<difficult>0</difficult>
		<bndbox>
			<xmin>2080</xmin>
			<ymin>2374</ymin>
			<xmax>2343</xmax>
			<ymax>2974</ymax>
		</bndbox>
	</object>
	<object>
		<name>LB</name>
		<pose>Unspecified</pose>
		<truncated>0</truncated>
		<difficult>0</difficult>
		<bndbox>
			<xmin>2320</xmin>
			<ymin>2197</ymin>
			<xmax>2454</xmax>
			<ymax>2377</ymax>
		</bndbox>
	</object>
</annotation>
