<annotation>
	<folder>images</folder>
	<filename>potato-1562.jpg</filename>
	<path>E:\mixed\potato\images\potato-1562.jpg</path>
	<source>
		<database>Unknown</database>
	</source>
	<size>
		<width>5760</width>
		<height>4312</height>
		<depth>3</depth>
	</size>
	<segmented>0</segmented>
	<object>
		<name>PM</name>
		<pose>Unspecified</pose>
		<truncated>0</truncated>
		<difficult>0</difficult>
		<bndbox>
			<xmin>2925</xmin>
			<ymin>1029</ymin>
			<xmax>3504</xmax>
			<ymax>1518</ymax>
		</bndbox>
	</object>
	<object>
		<name>LB</name>
		<pose>Unspecified</pose>
		<truncated>0</truncated>
		<difficult>0</difficult>
		<bndbox>
			<xmin>2767</xmin>
			<ymin>2040</ymin>
			<xmax>3393</xmax>
			<ymax>2511</ymax>
		</bndbox>
	</object>
	<object>
		<name>LB</name>
		<pose>Unspecified</pose>
		<truncated>0</truncated>
		<difficult>0</difficult>
		<bndbox>
			<xmin>3096</xmin>
			<ymin>1927</ymin>
			<xmax>3260</xmax>
			<ymax>2062</ymax>
		</bndbox>
	</object>
	<object>
		<name>LB</name>
		<pose>Unspecified</pose>
		<truncated>0</truncated>
		<difficult>0</difficult>
		<bndbox>
			<xmin>2616</xmin>
			<ymin>2144</ymin>
			<xmax>2771</xmax>
			<ymax>2389</ymax>
		</bndbox>
	</object>
</annotation>
