<annotation>
	<folder>images</folder>
	<filename>potato-837.jpg</filename>
	<path>E:\mixed\potato\images\potato-837.jpg</path>
	<source>
		<database>Unknown</database>
	</source>
	<size>
		<width>3120</width>
		<height>4160</height>
		<depth>3</depth>
	</size>
	<segmented>0</segmented>
	<object>
		<name>LB</name>
		<pose>Unspecified</pose>
		<truncated>0</truncated>
		<difficult>0</difficult>
		<bndbox>
			<xmin>1635</xmin>
			<ymin>421</ymin>
			<xmax>1753</xmax>
			<ymax>557</ymax>
		</bndbox>
	</object>
	<object>
		<name>LB</name>
		<pose>Unspecified</pose>
		<truncated>0</truncated>
		<difficult>0</difficult>
		<bndbox>
			<xmin>1538</xmin>
			<ymin>1445</ymin>
			<xmax>1777</xmax>
			<ymax>1919</ymax>
		</bndbox>
	</object>
	<object>
		<name>LB</name>
		<pose>Unspecified</pose>
		<truncated>0</truncated>
		<difficult>0</difficult>
		<bndbox>
			<xmin>842</xmin>
			<ymin>2379</ymin>
			<xmax>1116</xmax>
			<ymax>2645</ymax>
		</bndbox>
	</object>
	<object>
		<name>LB</name>
		<pose>Unspecified</pose>
		<truncated>0</truncated>
		<difficult>0</difficult>
		<bndbox>
			<xmin>2442</xmin>
			<ymin>1549</ymin>
			<xmax>2720</xmax>
			<ymax>1888</ymax>
		</bndbox>
	</object>
	<object>
		<name>LB</name>
		<pose>Unspecified</pose>
		<truncated>0</truncated>
		<difficult>0</difficult>
		<bndbox>
			<xmin>1864</xmin>
			<ymin>3688</ymin>
			<xmax>2103</xmax>
			<ymax>3853</ymax>
		</bndbox>
	</object>
	<object>
		<name>LB</name>
		<pose>Unspecified</pose>
		<truncated>0</truncated>
		<difficult>0</difficult>
		<bndbox>
			<xmin>1329</xmin>
			<ymin>3384</ymin>
			<xmax>1564</xmax>
			<ymax>3836</ymax>
		</bndbox>
	</object>
	<object>
		<name>LB</name>
		<pose>Unspecified</pose>
		<truncated>0</truncated>
		<difficult>0</difficult>
		<bndbox>
			<xmin>2894</xmin>
			<ymin>2210</ymin>
			<xmax>3085</xmax>
			<ymax>2527</ymax>
		</bndbox>
	</object>
</annotation>
