<annotation>
	<folder>images</folder>
	<filename>potato-48.jpg</filename>
	<path>E:\mixed\potato\images\potato-48.jpg</path>
	<source>
		<database>Unknown</database>
	</source>
	<size>
		<width>4312</width>
		<height>5760</height>
		<depth>3</depth>
	</size>
	<segmented>0</segmented>
	<object>
		<name>LB</name>
		<pose>Unspecified</pose>
		<truncated>0</truncated>
		<difficult>0</difficult>
		<bndbox>
			<xmin>2225</xmin>
			<ymin>4625</ymin>
			<xmax>2463</xmax>
			<ymax>5289</ymax>
		</bndbox>
	</object>
	<object>
		<name>LB</name>
		<pose>Unspecified</pose>
		<truncated>0</truncated>
		<difficult>0</difficult>
		<bndbox>
			<xmin>2889</xmin>
			<ymin>2783</ymin>
			<xmax>3341</xmax>
			<ymax>3157</ymax>
		</bndbox>
	</object>
	<object>
		<name>LB</name>
		<pose>Unspecified</pose>
		<truncated>0</truncated>
		<difficult>0</difficult>
		<bndbox>
			<xmin>2460</xmin>
			<ymin>3002</ymin>
			<xmax>2876</xmax>
			<ymax>3551</ymax>
		</bndbox>
	</object>
	<object>
		<name>LB</name>
		<pose>Unspecified</pose>
		<truncated>0</truncated>
		<difficult>0</difficult>
		<bndbox>
			<xmin>2654</xmin>
			<ymin>3202</ymin>
			<xmax>3247</xmax>
			<ymax>3728</ymax>
		</bndbox>
	</object>
	<object>
		<name>LB</name>
		<pose>Unspecified</pose>
		<truncated>0</truncated>
		<difficult>0</difficult>
		<bndbox>
			<xmin>1393</xmin>
			<ymin>3376</ymin>
			<xmax>1667</xmax>
			<ymax>3525</ymax>
		</bndbox>
	</object>
	<object>
		<name>LB</name>
		<pose>Unspecified</pose>
		<truncated>0</truncated>
		<difficult>0</difficult>
		<bndbox>
			<xmin>1864</xmin>
			<ymin>3083</ymin>
			<xmax>2118</xmax>
			<ymax>3496</ymax>
		</bndbox>
	</object>
	<object>
		<name>LB</name>
		<pose>Unspecified</pose>
		<truncated>0</truncated>
		<difficult>0</difficult>
		<bndbox>
			<xmin>2118</xmin>
			<ymin>2247</ymin>
			<xmax>2386</xmax>
			<ymax>2522</ymax>
		</bndbox>
	</object>
	<object>
		<name>LB</name>
		<pose>Unspecified</pose>
		<truncated>0</truncated>
		<difficult>0</difficult>
		<bndbox>
			<xmin>2386</xmin>
			<ymin>2409</ymin>
			<xmax>2586</xmax>
			<ymax>2654</ymax>
		</bndbox>
	</object>
	<object>
		<name>BG</name>
		<pose>Unspecified</pose>
		<truncated>0</truncated>
		<difficult>0</difficult>
		<bndbox>
			<xmin>199</xmin>
			<ymin>2480</ymin>
			<xmax>974</xmax>
			<ymax>3299</ymax>
		</bndbox>
	</object>
	<object>
		<name>BG</name>
		<pose>Unspecified</pose>
		<truncated>0</truncated>
		<difficult>0</difficult>
		<bndbox>
			<xmin>455</xmin>
			<ymin>1249</ymin>
			<xmax>1999</xmax>
			<ymax>2243</ymax>
		</bndbox>
	</object>
	<object>
		<name>BG</name>
		<pose>Unspecified</pose>
		<truncated>0</truncated>
		<difficult>0</difficult>
		<bndbox>
			<xmin>1438</xmin>
			<ymin>3637</ymin>
			<xmax>2012</xmax>
			<ymax>4353</ymax>
		</bndbox>
	</object>
	<object>
		<name>BG</name>
		<pose>Unspecified</pose>
		<truncated>0</truncated>
		<difficult>0</difficult>
		<bndbox>
			<xmin>1746</xmin>
			<ymin>2472</ymin>
			<xmax>2227</xmax>
			<ymax>2918</ymax>
		</bndbox>
	</object>
	<object>
		<name>LB</name>
		<pose>Unspecified</pose>
		<truncated>0</truncated>
		<difficult>0</difficult>
		<bndbox>
			<xmin>3116</xmin>
			<ymin>2536</ymin>
			<xmax>3255</xmax>
			<ymax>2705</ymax>
		</bndbox>
	</object>
	<object>
		<name>LB</name>
		<pose>Unspecified</pose>
		<truncated>0</truncated>
		<difficult>0</difficult>
		<bndbox>
			<xmin>2863</xmin>
			<ymin>2654</ymin>
			<xmax>3086</xmax>
			<ymax>2824</ymax>
		</bndbox>
	</object>
</annotation>
