<annotation>
	<folder>images</folder>
	<filename>potato-1187.jpg</filename>
	<path>E:\mixed\potato\images\potato-1187.jpg</path>
	<source>
		<database>Unknown</database>
	</source>
	<size>
		<width>4312</width>
		<height>5760</height>
		<depth>3</depth>
	</size>
	<segmented>0</segmented>
	<object>
		<name>LB</name>
		<pose>Unspecified</pose>
		<truncated>0</truncated>
		<difficult>0</difficult>
		<bndbox>
			<xmin>1693</xmin>
			<ymin>1324</ymin>
			<xmax>3087</xmax>
			<ymax>2436</ymax>
		</bndbox>
	</object>
	<object>
		<name>LB</name>
		<pose>Unspecified</pose>
		<truncated>0</truncated>
		<difficult>0</difficult>
		<bndbox>
			<xmin>3743</xmin>
			<ymin>5011</ymin>
			<xmax>4293</xmax>
			<ymax>5592</ymax>
		</bndbox>
	</object>
	<object>
		<name>LB</name>
		<pose>Unspecified</pose>
		<truncated>0</truncated>
		<difficult>0</difficult>
		<bndbox>
			<xmin>1219</xmin>
			<ymin>2730</ymin>
			<xmax>1946</xmax>
			<ymax>3403</ymax>
		</bndbox>
	</object>
	<object>
		<name>LB</name>
		<pose>Unspecified</pose>
		<truncated>0</truncated>
		<difficult>0</difficult>
		<bndbox>
			<xmin>1604</xmin>
			<ymin>2376</ymin>
			<xmax>2496</xmax>
			<ymax>2880</ymax>
		</bndbox>
	</object>
	<object>
		<name>LB</name>
		<pose>Unspecified</pose>
		<truncated>0</truncated>
		<difficult>0</difficult>
		<bndbox>
			<xmin>42</xmin>
			<ymin>1834</ymin>
			<xmax>619</xmax>
			<ymax>2361</ymax>
		</bndbox>
	</object>
	<object>
		<name>LB</name>
		<pose>Unspecified</pose>
		<truncated>0</truncated>
		<difficult>0</difficult>
		<bndbox>
			<xmin>577</xmin>
			<ymin>934</ymin>
			<xmax>1696</xmax>
			<ymax>2007</ymax>
		</bndbox>
	</object>
	<object>
		<name>LB</name>
		<pose>Unspecified</pose>
		<truncated>0</truncated>
		<difficult>0</difficult>
		<bndbox>
			<xmin>81</xmin>
			<ymin>761</ymin>
			<xmax>450</xmax>
			<ymax>1041</ymax>
		</bndbox>
	</object>
</annotation>
