<annotation>
	<folder>images</folder>
	<filename>potato-1969.jpg</filename>
	<path>E:\mixed\potato\images\potato-1969.jpg</path>
	<source>
		<database>Unknown</database>
	</source>
	<size>
		<width>5760</width>
		<height>4312</height>
		<depth>3</depth>
	</size>
	<segmented>0</segmented>
	<object>
		<name>LB</name>
		<pose>Unspecified</pose>
		<truncated>0</truncated>
		<difficult>0</difficult>
		<bndbox>
			<xmin>2500</xmin>
			<ymin>2264</ymin>
			<xmax>2980</xmax>
			<ymax>2780</ymax>
		</bndbox>
	</object>
	<object>
		<name>LB</name>
		<pose>Unspecified</pose>
		<truncated>0</truncated>
		<difficult>0</difficult>
		<bndbox>
			<xmin>2396</xmin>
			<ymin>3220</ymin>
			<xmax>2588</xmax>
			<ymax>3576</ymax>
		</bndbox>
	</object>
	<object>
		<name>LB</name>
		<pose>Unspecified</pose>
		<truncated>0</truncated>
		<difficult>0</difficult>
		<bndbox>
			<xmin>2492</xmin>
			<ymin>2960</ymin>
			<xmax>2620</xmax>
			<ymax>3140</ymax>
		</bndbox>
	</object>
	<object>
		<name>LB</name>
		<pose>Unspecified</pose>
		<truncated>0</truncated>
		<difficult>0</difficult>
		<bndbox>
			<xmin>1304</xmin>
			<ymin>2704</ymin>
			<xmax>1660</xmax>
			<ymax>3308</ymax>
		</bndbox>
	</object>
	<object>
		<name>LB</name>
		<pose>Unspecified</pose>
		<truncated>0</truncated>
		<difficult>0</difficult>
		<bndbox>
			<xmin>2088</xmin>
			<ymin>3436</ymin>
			<xmax>2348</xmax>
			<ymax>3712</ymax>
		</bndbox>
	</object>
</annotation>
