<annotation>
	<folder>images</folder>
	<filename>potato-62.jpg</filename>
	<path>E:\mixed\potato\images\potato-62.jpg</path>
	<source>
		<database>Unknown</database>
	</source>
	<size>
		<width>4312</width>
		<height>5760</height>
		<depth>3</depth>
	</size>
	<segmented>0</segmented>
	<object>
		<name>LB</name>
		<pose>Unspecified</pose>
		<truncated>1</truncated>
		<difficult>0</difficult>
		<bndbox>
			<xmin>2211</xmin>
			<ymin>20</ymin>
			<xmax>4312</xmax>
			<ymax>2690</ymax>
		</bndbox>
	</object>
	<object>
		<name>LB</name>
		<pose>Unspecified</pose>
		<truncated>1</truncated>
		<difficult>0</difficult>
		<bndbox>
			<xmin>1</xmin>
			<ymin>3061</ymin>
			<xmax>1337</xmax>
			<ymax>4325</ymax>
		</bndbox>
	</object>
	<object>
		<name>LB</name>
		<pose>Unspecified</pose>
		<truncated>0</truncated>
		<difficult>0</difficult>
		<bndbox>
			<xmin>1928</xmin>
			<ymin>2843</ymin>
			<xmax>2192</xmax>
			<ymax>3097</ymax>
		</bndbox>
	</object>
	<object>
		<name>LB</name>
		<pose>Unspecified</pose>
		<truncated>0</truncated>
		<difficult>0</difficult>
		<bndbox>
			<xmin>2246</xmin>
			<ymin>2897</ymin>
			<xmax>3155</xmax>
			<ymax>3679</ymax>
		</bndbox>
	</object>
	<object>
		<name>LB</name>
		<pose>Unspecified</pose>
		<truncated>0</truncated>
		<difficult>0</difficult>
		<bndbox>
			<xmin>1565</xmin>
			<ymin>3025</ymin>
			<xmax>1883</xmax>
			<ymax>3352</ymax>
		</bndbox>
	</object>
	<object>
		<name>LB</name>
		<pose>Unspecified</pose>
		<truncated>0</truncated>
		<difficult>0</difficult>
		<bndbox>
			<xmin>837</xmin>
			<ymin>1025</ymin>
			<xmax>1983</xmax>
			<ymax>2297</ymax>
		</bndbox>
	</object>
	<object>
		<name>LB</name>
		<pose>Unspecified</pose>
		<truncated>0</truncated>
		<difficult>0</difficult>
		<bndbox>
			<xmin>1937</xmin>
			<ymin>1770</ymin>
			<xmax>2665</xmax>
			<ymax>2506</ymax>
		</bndbox>
	</object>
	<object>
		<name>LB</name>
		<pose>Unspecified</pose>
		<truncated>0</truncated>
		<difficult>0</difficult>
		<bndbox>
			<xmin>2055</xmin>
			<ymin>4797</ymin>
			<xmax>2782</xmax>
			<ymax>5680</ymax>
		</bndbox>
	</object>
	<object>
		<name>LB</name>
		<pose>Unspecified</pose>
		<truncated>0</truncated>
		<difficult>0</difficult>
		<bndbox>
			<xmin>1567</xmin>
			<ymin>3970</ymin>
			<xmax>1839</xmax>
			<ymax>4318</ymax>
		</bndbox>
	</object>
	<object>
		<name>LB</name>
		<pose>Unspecified</pose>
		<truncated>0</truncated>
		<difficult>0</difficult>
		<bndbox>
			<xmin>1196</xmin>
			<ymin>4723</ymin>
			<xmax>1805</xmax>
			<ymax>5251</ymax>
		</bndbox>
	</object>
	<object>
		<name>LB</name>
		<pose>Unspecified</pose>
		<truncated>1</truncated>
		<difficult>0</difficult>
		<bndbox>
			<xmin>596</xmin>
			<ymin>5475</ymin>
			<xmax>1367</xmax>
			<ymax>5760</ymax>
		</bndbox>
	</object>
	<object>
		<name>LB</name>
		<pose>Unspecified</pose>
		<truncated>0</truncated>
		<difficult>0</difficult>
		<bndbox>
			<xmin>1577</xmin>
			<ymin>5237</ymin>
			<xmax>1715</xmax>
			<ymax>5456</ymax>
		</bndbox>
	</object>
</annotation>
