<annotation>
	<folder>images</folder>
	<filename>potato-820.jpg</filename>
	<path>E:\mixed\potato\images\potato-820.jpg</path>
	<source>
		<database>Unknown</database>
	</source>
	<size>
		<width>4160</width>
		<height>3120</height>
		<depth>3</depth>
	</size>
	<segmented>0</segmented>
	<object>
		<name>LB</name>
		<pose>Unspecified</pose>
		<truncated>0</truncated>
		<difficult>0</difficult>
		<bndbox>
			<xmin>3060</xmin>
			<ymin>1897</ymin>
			<xmax>3253</xmax>
			<ymax>2129</ymax>
		</bndbox>
	</object>
	<object>
		<name>LB</name>
		<pose>Unspecified</pose>
		<truncated>0</truncated>
		<difficult>0</difficult>
		<bndbox>
			<xmin>2928</xmin>
			<ymin>2171</ymin>
			<xmax>3043</xmax>
			<ymax>2256</ymax>
		</bndbox>
	</object>
	<object>
		<name>LB</name>
		<pose>Unspecified</pose>
		<truncated>0</truncated>
		<difficult>0</difficult>
		<bndbox>
			<xmin>2599</xmin>
			<ymin>2826</ymin>
			<xmax>2728</xmax>
			<ymax>2945</ymax>
		</bndbox>
	</object>
	<object>
		<name>LB</name>
		<pose>Unspecified</pose>
		<truncated>0</truncated>
		<difficult>0</difficult>
		<bndbox>
			<xmin>2641</xmin>
			<ymin>2955</ymin>
			<xmax>2760</xmax>
			<ymax>3048</ymax>
		</bndbox>
	</object>
	<object>
		<name>LB</name>
		<pose>Unspecified</pose>
		<truncated>0</truncated>
		<difficult>0</difficult>
		<bndbox>
			<xmin>2747</xmin>
			<ymin>1039</ymin>
			<xmax>2934</xmax>
			<ymax>1135</ymax>
		</bndbox>
	</object>
	<object>
		<name>LB</name>
		<pose>Unspecified</pose>
		<truncated>0</truncated>
		<difficult>0</difficult>
		<bndbox>
			<xmin>1146</xmin>
			<ymin>1127</ymin>
			<xmax>1572</xmax>
			<ymax>1459</ymax>
		</bndbox>
	</object>
	<object>
		<name>LB</name>
		<pose>Unspecified</pose>
		<truncated>0</truncated>
		<difficult>0</difficult>
		<bndbox>
			<xmin>983</xmin>
			<ymin>1551</ymin>
			<xmax>1319</xmax>
			<ymax>1855</ymax>
		</bndbox>
	</object>
	<object>
		<name>LB</name>
		<pose>Unspecified</pose>
		<truncated>0</truncated>
		<difficult>0</difficult>
		<bndbox>
			<xmin>2362</xmin>
			<ymin>1378</ymin>
			<xmax>2721</xmax>
			<ymax>1666</ymax>
		</bndbox>
	</object>
	<object>
		<name>LB</name>
		<pose>Unspecified</pose>
		<truncated>0</truncated>
		<difficult>0</difficult>
		<bndbox>
			<xmin>2209</xmin>
			<ymin>1661</ymin>
			<xmax>2584</xmax>
			<ymax>1939</ymax>
		</bndbox>
	</object>
	<object>
		<name>LB</name>
		<pose>Unspecified</pose>
		<truncated>0</truncated>
		<difficult>0</difficult>
		<bndbox>
			<xmin>1999</xmin>
			<ymin>1912</ymin>
			<xmax>2214</xmax>
			<ymax>2110</ymax>
		</bndbox>
	</object>
</annotation>
